skymapper/__init__.py
skymapper/healpix.py
skymapper/map.py
skymapper/projection.py
skymapper/survey/__init__.py
skymapper/survey/boss_survey.ply
skymapper/survey/des-round17-poly_tidy.ply
skymapper-0.4.7.dist-info/LICENSE.md
skymapper-0.4.7.dist-info/METADATA
skymapper-0.4.7.dist-info/WHEEL
skymapper-0.4.7.dist-info/top_level.txt
skymapper-0.4.7.dist-info/RECORD
