Metadata-Version: 2.1
Name: skymapper
Version: 0.4.7
Summary: Mapping astronomical survey data on the sky, handsomely
Home-page: https://github.com/pmelchior/skymapper
Author: Peter Melchior
Author-email: peter.m.melchior@gmail.com
License: MIT
Keywords: visualization,map projection,matplotlib
Classifier: Development Status :: 4 - Beta
Classifier: License :: OSI Approved :: MIT License
Classifier: Intended Audience :: Developers
Classifier: Intended Audience :: Education
Classifier: Intended Audience :: Science/Research
Classifier: Operating System :: OS Independent
Classifier: Programming Language :: Python
Classifier: Topic :: Scientific/Engineering :: Astronomy
License-File: LICENSE.md
Requires-Dist: matplotlib
Requires-Dist: numpy
Requires-Dist: scipy
Requires-Dist: healpy
